django_dataexporter/__init__.py
django_dataexporter/admin.py
django_dataexporter/base.py
django_dataexporter/csv.py
django_dataexporter/excel.py
django_dataexporter-2.1.0.dist-info/METADATA
django_dataexporter-2.1.0.dist-info/WHEEL
django_dataexporter-2.1.0.dist-info/licenses/LICENSE.rst
django_dataexporter-2.1.0.dist-info/RECORD
