Metadata-Version: 2.4
Name: django-dataexporter
Version: 2.1.0
Summary: Extensible helper to export Django QuerySets and other data to CSV and Excel.
Project-URL: Homepage, https://github.com/lenarother/django-dataexporter
Project-URL: Repository, https://github.com/lenarother/django-dataexporter
Author-email: Stephan Jaekel <steph@rdev.info>, Magdalena Rother <rother.magdalena@gmail.com>
License: MIT
License-File: LICENSE.rst
Classifier: Development Status :: 5 - Production/Stable
Classifier: Environment :: Web Environment
Classifier: Framework :: Django
Classifier: Intended Audience :: Developers
Classifier: License :: OSI Approved :: MIT License
Classifier: Operating System :: Unix
Classifier: Programming Language :: Python
Classifier: Programming Language :: Python :: 3
Requires-Python: <4,>=3.10
Requires-Dist: django>=3.2
Requires-Dist: openpyxl>=2.6
Provides-Extra: dev
Requires-Dist: coverage[toml]>=5.5; extra == 'dev'
Requires-Dist: pre-commit>=3.0; extra == 'dev'
Requires-Dist: pytest-cov>=2.11; extra == 'dev'
Requires-Dist: pytest-django>=4.2; extra == 'dev'
Requires-Dist: pytest-snapshot>=0.6; extra == 'dev'
Requires-Dist: pytest>=6.2; extra == 'dev'
Requires-Dist: ruff>=0.8; extra == 'dev'
Requires-Dist: tox-uv>=1.0; extra == 'dev'
Requires-Dist: tox>=4.0; extra == 'dev'
Provides-Extra: docs
Requires-Dist: sphinx>=3.5; extra == 'docs'
